google/cloud/gke_multicloud/__init__.py
google/cloud/gke_multicloud/gapic_version.py
google/cloud/gke_multicloud/py.typed
google/cloud/gke_multicloud_v1/__init__.py
google/cloud/gke_multicloud_v1/gapic_metadata.json
google/cloud/gke_multicloud_v1/gapic_version.py
google/cloud/gke_multicloud_v1/py.typed
google/cloud/gke_multicloud_v1/services/__init__.py
google/cloud/gke_multicloud_v1/services/attached_clusters/__init__.py
google/cloud/gke_multicloud_v1/services/attached_clusters/async_client.py
google/cloud/gke_multicloud_v1/services/attached_clusters/client.py
google/cloud/gke_multicloud_v1/services/attached_clusters/pagers.py
google/cloud/gke_multicloud_v1/services/attached_clusters/transports/__init__.py
google/cloud/gke_multicloud_v1/services/attached_clusters/transports/base.py
google/cloud/gke_multicloud_v1/services/attached_clusters/transports/grpc.py
google/cloud/gke_multicloud_v1/services/attached_clusters/transports/grpc_asyncio.py
google/cloud/gke_multicloud_v1/services/attached_clusters/transports/rest.py
google/cloud/gke_multicloud_v1/services/attached_clusters/transports/rest_base.py
google/cloud/gke_multicloud_v1/services/aws_clusters/__init__.py
google/cloud/gke_multicloud_v1/services/aws_clusters/async_client.py
google/cloud/gke_multicloud_v1/services/aws_clusters/client.py
google/cloud/gke_multicloud_v1/services/aws_clusters/pagers.py
google/cloud/gke_multicloud_v1/services/aws_clusters/transports/__init__.py
google/cloud/gke_multicloud_v1/services/aws_clusters/transports/base.py
google/cloud/gke_multicloud_v1/services/aws_clusters/transports/grpc.py
google/cloud/gke_multicloud_v1/services/aws_clusters/transports/grpc_asyncio.py
google/cloud/gke_multicloud_v1/services/aws_clusters/transports/rest.py
google/cloud/gke_multicloud_v1/services/aws_clusters/transports/rest_base.py
google/cloud/gke_multicloud_v1/services/azure_clusters/__init__.py
google/cloud/gke_multicloud_v1/services/azure_clusters/async_client.py
google_cloud_gke_multicloud-0.7.0.dist-info/licenses/LICENSE
google_cloud_gke_multicloud-0.7.0.dist-info/METADATA
google_cloud_gke_multicloud-0.7.0.dist-info/WHEEL
google_cloud_gke_multicloud-0.7.0.dist-info/top_level.txt
google_cloud_gke_multicloud-0.7.0.dist-info/RECORD
